[{"id":1,"name":"Karlos","username":"Karlos2102","age":20,"email":"karlos.mirzakhanyan@gmail.com","phoneNumber":"093987789"},{"id":4,"name":"Karlos","username":"Karlos2102","age":20,"email":"karlos.mirzakhanyan@gmail.com","phoneNumber":"093987789"},{"id":5,"name":"la","username":"Karlos2102","age":20,"email":"karlos.mirzakhanyan@gmail.com","phoneNumber":"093987789"},{"id":6,"name":"la","username":"Karlos2102","age":20,"email":"karlos.mirzakhanyan@gmail.com","phoneNumber":"093987789"},{"id":7,"name":"la","username":"Karlos2102","age":20,"email":"karlos.mirzakhanyan@gmail.com","phoneNumber":"093987789"}]